pip_helloworld_test/__init__.py
pip_helloworld_test/main.py
pip_helloworld_test-0.1.dist-info/METADATA
pip_helloworld_test-0.1.dist-info/WHEEL
pip_helloworld_test-0.1.dist-info/entry_points.txt
pip_helloworld_test-0.1.dist-info/top_level.txt
pip_helloworld_test-0.1.dist-info/RECORD
