Metadata-Version: 2.1
Name: pip-helloworld-test
Version: 0.1
Summary: A simple package that prints Hello, World!
Home-page: UNKNOWN
Author: Mahesh Karre
Author-email: your.email@example.com
License: UNKNOWN
Platform: UNKNOWN
